pyZink/__init__.py
pyZink/time.py
pyZink/connect/__init__.py
pyZink/connect/arp.py
pyZink/connect/ssh.py
pyZink/connect/tcp.py
pyZink-0.1.2.dist-info/LICENSE
pyZink-0.1.2.dist-info/METADATA
pyZink-0.1.2.dist-info/WHEEL
pyZink-0.1.2.dist-info/top_level.txt
pyZink-0.1.2.dist-info/RECORD
