Metadata-Version: 2.1
Name: pyZink
Version: 0.1.2
Summary: Python functionality that I use on a regular basis, that others might find use or inspiration from.
Home-page: https://github.com/Peasniped/pyZink
Author: Cernott
Author-email: pyZink@znk.dk
Classifier: Programming Language :: Python :: 3
Classifier: License :: OSI Approved :: GNU General Public License v3 (GPLv3)
Classifier: Operating System :: OS Independent
License-File: LICENSE
Requires-Dist: paramiko ==3.4.0
Requires-Dist: scapy ==2.5.0
